odoo/addons/loyalty_program_chatter/README.rst
odoo/addons/loyalty_program_chatter/__init__.py
odoo/addons/loyalty_program_chatter/__manifest__.py
odoo/addons/loyalty_program_chatter/i18n/ca.po
odoo/addons/loyalty_program_chatter/i18n/es.po
odoo/addons/loyalty_program_chatter/i18n/it.po
odoo/addons/loyalty_program_chatter/i18n/loyalty_program_chatter.pot
odoo/addons/loyalty_program_chatter/models/__init__.py
odoo/addons/loyalty_program_chatter/models/loyalty_program.py
odoo/addons/loyalty_program_chatter/readme/CONTRIBUTORS.md
odoo/addons/loyalty_program_chatter/readme/DESCRIPTION.md
odoo/addons/loyalty_program_chatter/readme/USAGE.md
odoo/addons/loyalty_program_chatter/static/description/icon.png
odoo/addons/loyalty_program_chatter/static/description/index.html
odoo/addons/loyalty_program_chatter/views/loyalty_program_view.xml
odoo_addon_loyalty_program_chatter-18.0.1.0.0.2.dist-info/METADATA
odoo_addon_loyalty_program_chatter-18.0.1.0.0.2.dist-info/WHEEL
odoo_addon_loyalty_program_chatter-18.0.1.0.0.2.dist-info/top_level.txt
odoo_addon_loyalty_program_chatter-18.0.1.0.0.2.dist-info/RECORD
